speedwagon_algorithm/__init__.py
speedwagon_algorithm/modules.py
speedwagon_algorithm-1.9.1.dist-info/METADATA
speedwagon_algorithm-1.9.1.dist-info/WHEEL
speedwagon_algorithm-1.9.1.dist-info/top_level.txt
speedwagon_algorithm-1.9.1.dist-info/RECORD
