Metadata-Version: 2.1
Name: speedwagon_algorithm
Version: 1.9.1
Summary: Speedwagon Algorithm is a basic and easy to use/implement asymmetric encryption algorithm.
Home-page: https://github.com/muhammedikbalyildiz/speedwagon_algorithm
Author: muhammedikbalyildiz
Author-email: muhammedikbalyildiz@proton.me
